README.txt
setup.cfg
setup.py
src/koansys/__init__.py
src/koansys.recipe.hooks.egg-info/PKG-INFO
src/koansys.recipe.hooks.egg-info/SOURCES.txt
src/koansys.recipe.hooks.egg-info/dependency_links.txt
src/koansys.recipe.hooks.egg-info/entry_points.txt
src/koansys.recipe.hooks.egg-info/namespace_packages.txt
src/koansys.recipe.hooks.egg-info/not-zip-safe
src/koansys.recipe.hooks.egg-info/requires.txt
src/koansys.recipe.hooks.egg-info/top_level.txt
src/koansys/recipe/__init__.py
src/koansys/recipe/hooks/__init__.py
src/koansys/recipe/hooks/tests.py
