Metadata-Version: 1.0
Name: koansys.recipe.hooks
Version: 0.1-dev-r5
Summary: zc.buildout recipe to run python methods as hooks
Home-page: http://koansys-recipe-hooks.googlecode.com/svn/trunk
Author: Chris Shenton
Author-email: chris@koansys.com
License: GPL
Keywords: buildout
Platform: UNKNOWN
Classifier: Framework :: Buildout
